langchain_fireworks/__init__.py
langchain_fireworks/_compat.py
langchain_fireworks/chat_models.py
langchain_fireworks/embeddings.py
langchain_fireworks/llms.py
langchain_fireworks/py.typed
langchain_fireworks/version.py
langchain_fireworks-1.0.0.dist-info/METADATA
langchain_fireworks-1.0.0.dist-info/WHEEL
langchain_fireworks-1.0.0.dist-info/licenses/LICENSE
langchain_fireworks-1.0.0.dist-info/RECORD
